[
  {
    "id": "cat",
    "name_cz": "Kočka",
    "name_en": "Cat",
    "name_vi": "Con mèo",
    "image": "images/cat.png",
    "sound": "sounds/cat.wav",
    "sound_cz": "sounds/kocka.mp3",
    "sound_en": "sounds/cat_en.mp3",
    "sound_vi": "sounds/con_meo.mp3"
  },
  {
    "id": "monkey",
    "name_cz": "Opice",
    "name_en": "Monkey",
    "name_vi": "Con khỉ",
    "image": "images/monkey.png",
    "sound": "sounds/monkey.wav",
    "sound_cz": "sounds/opice.mp3",
    "sound_en": "sounds/monkey_en.mp3",
    "sound_vi": "sounds/con_khi.mp3"	
  },
  {
    "id": "tiger",
    "name_cz": "Tygr",
    "name_en": "Tiger",
    "name_vi": "Con hổ",
    "image": "images/tiger.png",
    "sound": "sounds/tiger.mp3",
    "sound_cz": "sounds/tygr.mp3",
    "sound_en": "sounds/tiger_en.mp3",
    "sound_vi": "sounds/con_ho.mp3"	
  },
  {
    "id": "elephant",
    "name_cz": "Slon",
    "name_en": "Elephant",
    "name_vi": "Con voi",
    "image": "images/elephant.png",
    "sound": "sounds/elephant.mp3",
    "sound_cz": "sounds/slon.mp3",
    "sound_en": "sounds/elephant_en.mp3",
    "sound_vi": "sounds/con_voi.mp3"	
  },
  {
    "id": "rat",
    "name_cz": "Krysa",
    "name_en": "Rat",
    "name_vi": "Con chuột",
    "image": "images/rat.png",
    "sound": "sounds/rat.mp3",
    "sound_cz": "sounds/krysa.mp3",
    "sound_en": "sounds/rat_en.mp3",
    "sound_vi": "sounds/con_chuot.mp3"
  },
  {
    "id": "chicken",
    "name_cz": "Slepice",
    "name_en": "Chicken",
    "name_vi": "Con gà mái",
    "image": "images/chicken.png",
    "sound": "sounds/chicken.mp3",
    "sound_cz": "sounds/slepice.mp3",
    "sound_en": "sounds/chicken_en.mp3",
    "sound_vi": "sounds/con_ga_mai.mp3"
  },
  {
    "id": "dog",
    "name_cz": "Pes",
    "name_en": "Dog",
    "name_vi": "Con chó",
    "image": "images/dog.png",
    "sound": "sounds/dog.wav",
    "sound_cz": "sounds/pes.mp3",
    "sound_en": "sounds/dog_en.mp3",
    "sound_vi": "sounds/con_cho.mp3"
  },
  {
    "id": "duck",
    "name_cz": "Kachna",
    "name_en": "Duck",
    "name_vi": "Con vịt",
    "image": "images/duck.png",
    "sound": "sounds/duck.mp3",
    "sound_cz": "sounds/kachna.mp3",
    "sound_en": "sounds/duck_en.mp3",
    "sound_vi": "sounds/con_vit.mp3"
  },
  {
    "id": "lion",
    "name_cz": "Lev",
    "name_en": "Lion",
    "name_vi": "Con sư tử",
    "image": "images/lion.png",
    "sound": "sounds/lion.mp3",
    "sound_cz": "sounds/lev.mp3",
    "sound_en": "sounds/lion_en.mp3",
    "sound_vi": "sounds/con_su_tu.mp3"
  },
  {
    "id": "rooster",
    "name_cz": "Kohout",
    "name_en": "Rooster",
    "name_vi": "Con gà trống",
    "image": "images/rooster.png",
    "sound": "sounds/rooster.mp3",
    "sound_cz": "sounds/kohout.mp3",
    "sound_en": "sounds/rooster_en.mp3",
    "sound_vi": "sounds/con_ga_trong.mp3"
  },
  {
    "id": "pig",
    "name_cz": "Prase",
    "name_en": "Pig",
    "name_vi": "Con lợn",
    "image": "images/pig.png",
    "sound": "sounds/pig.mp3",
    "sound_cz": "sounds/prase.mp3",
    "sound_en": "sounds/pig_en.mp3",
    "sound_vi": "sounds/con_lon.mp3"
  },
  {
    "id": "horse",
    "name_cz": "Kůň",
    "name_en": "Horse",
    "name_vi": "Con ngựa",
    "image": "images/horse.png",
    "sound": "sounds/horse.wav",
    "sound_cz": "sounds/kun.mp3",
    "sound_en": "sounds/horse_en.mp3",
    "sound_vi": "sounds/con_ngua.mp3"
  },
  {
    "id": "cow",
    "name_cz": "Kráva",
    "name_en": "Cow",
    "name_vi": "Con bò",
    "image": "images/cow.png",
    "sound": "sounds/cow.wav",
    "sound_cz": "sounds/krava.mp3",
    "sound_en": "sounds/cow_en.mp3",
    "sound_vi": "sounds/con_bo.mp3"
  },
  {
    "id": "goat",
    "name_cz": "Koza",
    "name_en": "Goat",
    "name_vi": "Con dê",
    "image": "images/goat.png",
    "sound": "sounds/goat.mp3",
    "sound_cz": "sounds/koza.mp3",
    "sound_en": "sounds/goat_en.mp3",
    "sound_vi": "sounds/con_de.mp3"
  },
  {
    "id": "giraffe",
    "name_cz": "žirafa",
    "name_en": "Giraffe",
    "name_vi": "Hươu cao cổ",
    "image": "images/giraffe.png",
    "sound": "sounds/giraffe.mp3",
    "sound_cz": "sounds/zirafa.mp3",
    "sound_en": "sounds/giraffe_en.mp3",
    "sound_vi": "sounds/huou_cao_co.mp3"
  },
  {
    "id": "snake",
    "name_cz": "Had",
    "name_en": "Snake",
    "name_vi": "Con Rắn",
    "image": "images/snake.png",
    "sound": "sounds/snake.mp3",
    "sound_cz": "sounds/had.mp3",
    "sound_en": "sounds/snake_en.mp3",
    "sound_vi": "sounds/con_ran.mp3"
  },
  {
    "id": "crocodile",
    "name_cz": "Krokodýl",
    "name_en": "Crocodile",
    "name_vi": "Cá sấu",
    "image": "images/crocodile.png",
    "sound": "sounds/crocodile.mp3",
    "sound_cz": "sounds/krokodýl.mp3",
    "sound_en": "sounds/crocodile_en.mp3",
    "sound_vi": "sounds/ca_sau.mp3"
  },
  {
    "id": "crab",
    "name_cz": "Krab",
    "name_en": "Crab",
    "name_vi": "Con Cua",
    "image": "images/crab.png",
    "sound": "sounds/crab.mp3",
    "sound_cz": "sounds/krab.mp3",
    "sound_en": "sounds/crab_en.mp3",
    "sound_vi": "sounds/con_cua.mp3"
  },
  {
    "id": "bee",
    "name_cz": "Včela",
    "name_en": "Bee",
    "name_vi": "Con ong",
    "image": "images/bee.png",
    "sound": "sounds/bee.mp3",
    "sound_cz": "sounds/vcela.mp3",
    "sound_en": "sounds/bee_en.mp3",
    "sound_vi": "sounds/con_ong.mp3"
  },
  {
    "id": "butterfly",
    "name_cz": "Motýl",
    "name_en": "Butterfly",
    "name_vi": "Con Bướm",
    "image": "images/butterfly.png",
    "sound": "sounds/butterfly.mp3",
    "sound_cz": "sounds/motyl.mp3",
    "sound_en": "sounds/butterfly_en.mp3",
    "sound_vi": "sounds/con_buom.mp3"
  },
  {
    "id": "frog",
    "name_cz": "žába",
    "name_en": "Frog",
    "name_vi": "Con ếch",
    "image": "images/frog.png",
    "sound": "sounds/frog.mp3",
    "sound_cz": "sounds/zaba.mp3",
    "sound_en": "sounds/frog_en.mp3",
    "sound_vi": "sounds/con_ech.mp3"
  },
  {
    "id": "wolf",
    "name_cz": "Vlk",
    "name_en": "Wolf",
    "name_vi": "Con chó sói",
    "image": "images/wolf.png",
    "sound": "sounds/wolf.mp3",
    "sound_cz": "sounds/vlk.mp3",
    "sound_en": "sounds/wolf_en.mp3",
    "sound_vi": "sounds/con_cho_soi.mp3"
  }
]
